[
    {
        "name": "SanDisk Extreme Carte Mémoire MicroSDXC 128 Go + Adaptateur SD avec Performances Applicatives A2 Jusqu'à 160 Mo/s, Classe 10, U3, V30",
        "prices": [
            {
                "timestamp": "2021-04-22T12:02:30.624Z",
                "price": "20,34 €"
            }
        ],
        "link": "https://www.amazon.fr/microSDXC-SanDisk-Adaptateur-Performances-Applicatives/dp/B07FCMKK5X/ref=sr_1_5?_encoding=UTF8&c=ts&dchild=1&keywords=Informatique&qid=1619092903&s=electronics&sr=1-5&ts_id=2908498031"
    },
    {
        "name": "Sony WH-1000XM3 Casque sans fil Bluetooth à réduction de bruit (batterie 30h, capteur tactile, application Headphones Connect, fonction de charge rapide, Amazon Alexa, sans fil) Noir",
        "prices": [
            {
                "timestamp": "2021-04-22T12:02:57.711Z",
                "price": "269,99 €"
            },
            {
                "timestamp": "2021-04-22T12:03:13.726Z",
                "price": "269,99 €"
            }
        ],
        "link": "https://www.amazon.fr/Sony-WH-1000XM3-Casque-Bluetooth-r%C3%A9duction/dp/B07GDR2LYK?ref_=Oct_s9_apbd_otopr_hd_bw_bkDYQ3&pf_rd_r=YT8QYKNT5J98X5XPH5EM&pf_rd_p=94fc4d5f-c67e-5e77-915a-068d1cdec7a2&pf_rd_s=merchandised-search-10&pf_rd_t=BROWSE&pf_rd_i=682942031"
    }
]